{
    "type": "#ext-gen1489#",
    "description": "#ext-gen1484#",
    "configBasique": {
        "title": "Product list",
        "bType": "productList",
        "flex": 1,
        "champsConfig": {
            "simple": [
                {
                    "categorie": "#ext-gen1072#",
                    "champs": [
                        {
                            "type": "Ext.ux.TreePicker",
                            "config": {
                                "fieldLabel": "#ext-gen1073#",
                                "name": "singlePage"
                            }
                        },
                        {
                            "type": "Ext.form.field.Number",
                            "config": {
                                "fieldLabel": "#ext-gen1114#",
                                "name": "columns",
                                "allowBlank": false,
                                "editable": false,
                                "allowDecimals": false,
                                "minValue": 1,
                                "maxValue": 4
                            }
                        },
                        {
                            "type": "Ext.form.field.Checkbox",
                            "config": {
                                "fieldLabel": "#ext-gen1406#",
                                "name": "showOnlyTitle",
                                "inputValue": true
                            }
                        },
                        {
                            "type": "Ext.form.field.Number",
                            "config": {
                                "fieldLabel": "#ext-gen1407#",
                                "name": "summaryHeight",
                                "allowDecimals": false,
                                "minValue": 0,
                                "value": 80
                            }
                        }
                    ]
                },
                {
                    "categorie": "Products",
                    "champs": [
                        {
                            "type": "Rubedo.view.queryBuilderField",
                            "config": {
                                "fieldLabel": "#ext-gen1075#",
                                "name": "query",
                                "isProductQuery":true
                            }
                        },
                        {
                            "type": "Ext.form.field.Checkbox",
                            "config": {
                                "fieldLabel": "#ext-gen1447#",
                                "name": "magicQuery",
                                "inputValue": true
                            }
                        }
                    ]
                },
              {
                "categorie": "#ext-gen1473#",
                "champs": [
                  {
                    "type": "Ext.form.field.Checkbox",
                    "config": {
                      "fieldLabel": "#ext-gen1474#",
                      "name": "enableFOContrib",
                      "inputValue": true
                    }
                  },
                  {
                    "type": "Ext.ux.TreePicker",
                    "config": {
                      "fieldLabel": "#ext-gen1475#",
                      "name": "editorPageId"
                    }
                  }
                ]
              },
                {
                    "categorie": "#ext-gen1094#",
                    "champs": [
                        {
                            "type": "Ext.form.field.Number",
                            "config": {
                                "fieldLabel": "#ext-gen1095#",
                                "name": "pageSize",
                                "allowDecimals": false,
                                "minValue": 0
                            }
                        },
                        {
                            "type": "Ext.form.field.Number",
                            "config": {
                                "fieldLabel": "#ext-gen1096#",
                                "allowDecimals": false,
                                "name": "resultsSkip",
                                "minValue": 1
                            }
                        },
                        {
                            "type": "Ext.form.field.Checkbox",
                            "config": {
                                "fieldLabel": "#ext-gen1097#",
                                "name": "showPager",
                                "inputValue": true
                            }
                        }
                    ]
                },
                {
                    "categorie": "#ext-gen1476#",
                    "champs": [
                        {
                            "type": "Ext.form.field.Checkbox",
                            "config": {
                                "fieldLabel": "#ext-gen1476#",
                                "name": "infiniteScroll",
                                "inputValue": false
                            }
                        },
                        {
                            "type": "Ext.form.field.Number",
                            "config": {
                                "fieldLabel": "#ext-gen1477#",
                                "name": "scrollThreshold",
                                "allowDecimals": false,
                                "minValue": 50,
                                "value": 300
                            }
                        },
                        {
                            "type": "Ext.form.field.Number",
                            "config": {
                                "fieldLabel": "#ext-gen1478#",
                                "allowDecimals": false,
                                "name": "timeThreshold",
                                "minValue": 50,
                                "value": 200
                            }
                        }
                    ]
                },
                {
                    "categorie": "#ext-gen1479#",
                    "champs": [
                        {
                            "type": "Ext.form.field.Text",
                            "config": {
                                "fieldLabel": "#ext-gen1405#",
                                "name": "imageField",
                                "value": "image"
                            }
                        },
                        {
                            "type": "Ext.form.field.Number",
                            "config": {
                                "fieldLabel": "#ext-gen1090#",
                                "name": "imageHeight",
                                "allowDecimals": false,
                                "minValue": 0
                            }
                        },
                        {
                            "type": "Ext.form.field.Number",
                            "config": {
                                "fieldLabel": "#ext-gen1450#",
                                "name": "imageWidth",
                                "allowDecimals": false,
                                "minValue": 0
                            }
                        },
                        {
                            "type": "Ext.form.field.ComboBox",
                            "config": {
                                "fieldLabel": "#ext-gen1451#",
                                "name": "imageResizeMode",
                                "editable": false,
                                "forceSelection": true,
                                "queryMode": "local",
                                "store": [
                                    "boxed",
                                    "crop",
                                    "morph"
                                ]
                            }
                        }
                    ]
                }
            ],
            "avance": [
                {
                    "categorie": "#ext-gen1472#",
                    "champs": [
                        {
                            "type": "Rubedo.view.ACEField",
                            "config": {
                                "fieldLabel": "#ext-gen1452#",
                                "name": "customTemplate",
                                "defaultTemplateUrl": "blocks/productList.html",
                                "twigMode": false

                            }
                        },
                      {
                        "type": "Ext.form.field.Number",
                        "config": {
                          "fieldLabel": "#ext-gen1491#",
                          "name": "blockMinHeight",
                          "allowDecimals": false,
                          "editable": true,
                          "minValue": 0
                        }
                      }
                    ]
                }
            ],
          "csEvents":{
            "changePage":null,
            "addToCart":null
          }
        },
        "configBloc": {
            "columns": 1,
            "showOnlyTitle": false,
            "showPager": true,
            "filterByUser": false,
            "timeThreshold": 200,
            "scrollThreshold": 300,
            "imageField": "image",
            "imageResizeMode":"boxed",
            "infiniteScroll": false
        }
    },
    "category": "#ext-gen1431#",
    "bType": "productList",
    "id": "54e1daf0f05c1dd01c000037"
}
